jupyter_ai_client/__init__.py
jupyter_ai_connector/__init__.py
jupyter_ai_connector/_version.py
jupyter_ai_connector/app.py
jupyter_ai_connector/credential_detection.py
jupyter_ai_connector/mux.py
jupyter_ai_connector/auth/__init__.py
jupyter_ai_connector/auth/auth_state.py
jupyter_ai_connector/auth/browser_id.py
jupyter_ai_connector/auth/identity.py
jupyter_ai_connector/auth/token_store.py
jupyter_ai_connector/handlers/__init__.py
jupyter_ai_connector/handlers/base.py
jupyter_ai_connector/handlers/commands.py
jupyter_ai_connector/handlers/config.py
jupyter_ai_connector/handlers/dev_config.py
jupyter_ai_connector/handlers/events.py
jupyter_ai_connector/handlers/notebooks.py
jupyter_ai_connector/handlers/oauth.py
jupyter_ai_connector/handlers/sessions.py
jupyter_ai_connector/handlers/streams.py
jupyter_ai_extension/__init__.py
jupyter_ai_extension/_version.py
jupyter_ai_extension/labextension/package.json
jupyter_ai_extension/labextension/schemas/@jupyter-ai/jupyterlab-extension/package.json.orig
jupyter_ai_extension/labextension/schemas/@jupyter-ai/jupyterlab-extension/plugin.json
jupyter_ai_extension/labextension/static/00b26ac825e209505639.woff2
jupyter_ai_extension/labextension/static/036d4e95149b69ff9bcc.woff2
jupyter_ai_extension/labextension/static/07d8e303ce4fc12b4bb5.ttf
jupyter_ai_extension/labextension/static/08ce98e51b04d58945a3.ttf
jupyter_ai_extension/labextension/static/0cdd387c9590a1a9f979.woff2
jupyter_ai_extension/labextension/static/0d85ae7cc30f23790a7f.ttf
jupyter_ai_extension/labextension/static/0f60d1b897938ec918c8.woff2
jupyter_ai_extension/labextension/static/11e4dc8a6471ff6d6ee5.woff
jupyter_ai_extension/labextension/static/138ac28d1663b3037e9c.ttf
jupyter_ai_extension/labextension/static/181.ff29106e1cf772c101ea.js
jupyter_ai_extension/labextension/static/195.a4f152e31e82f19e0372.js
jupyter_ai_extension/labextension/static/1ae6bd7475590e97e7f1.woff
jupyter_ai_extension/labextension/static/1c67f068fea8bb09bf09.ttf
ainotebookdev-0.1.5.dist-info/METADATA
ainotebookdev-0.1.5.dist-info/WHEEL
ainotebookdev-0.1.5.dist-info/entry_points.txt
ainotebookdev-0.1.5.dist-info/RECORD
