Metadata-Version: 2.4
Name: ainotebookdev
Version: 0.1.5
Summary: Agentic AI for Jupyter notebook.
License-Expression: BSD-3-Clause
Classifier: Framework :: Jupyter
Classifier: Framework :: Jupyter :: JupyterLab
Classifier: Framework :: Jupyter :: JupyterLab :: 4
Classifier: Framework :: Jupyter :: JupyterLab :: Extensions
Classifier: Framework :: Jupyter :: JupyterLab :: Extensions :: Prebuilt
Classifier: License :: OSI Approved :: BSD License
Classifier: Programming Language :: Python
Classifier: Programming Language :: Python :: 3
Classifier: Programming Language :: Python :: 3.10
Classifier: Programming Language :: Python :: 3.11
Classifier: Programming Language :: Python :: 3.12
Requires-Python: >=3.10
Requires-Dist: cryptography>=41.0.0
Requires-Dist: httpx-sse>=0.3.0
Requires-Dist: httpx>=0.25.0
Requires-Dist: jupyter-server>=2.0.0
Requires-Dist: jupyterlab>=4.0.0
Requires-Dist: keyring>=24.0.0
